configmap_reader/__init__.py
configmap_reader/cli.py
configmap_reader/config_api.py
configmap_reader/config_dir.py
configmap_reader/main.py
configmap_reader-0.2.0.dist-info/METADATA
configmap_reader-0.2.0.dist-info/WHEEL
configmap_reader-0.2.0.dist-info/entry_points.txt
configmap_reader-0.2.0.dist-info/licenses/LICENSE
configmap_reader-0.2.0.dist-info/RECORD
