Metadata-Version: 2.4
Name: configmap_reader
Version: 0.2.0
Summary: microservice to read and return content of a configmap
License: MIT
License-File: LICENSE
Keywords: kafka
Author: Siak Hooi
Author-email: siakhooi@gmail.com
Requires-Python: >=3.10
Classifier: Development Status :: 4 - Beta
Classifier: Environment :: Console
Classifier: License :: OSI Approved :: MIT License
Classifier: Topic :: Utilities
Requires-Dist: fastapi (>=0.123.9,<0.124.0)
Requires-Dist: kubernetes (>=34.1.0,<35.0.0)
Requires-Dist: uvicorn[standard] (>=0.38.0,<0.39.0)
Project-URL: Bug Tracker, https://github.com/siakhooi/configmap-reader/issues
Project-URL: Documentation, https://github.com/siakhooi/configmap-reader/wiki
Project-URL: Homepage, https://github.com/siakhooi/configmap-reader
Project-URL: Repository, https://github.com/siakhooi/configmap-reader
